raysurfer/__init__.py
raysurfer/_version.py
raysurfer/client.py
raysurfer/exceptions.py
raysurfer/sdk_client.py
raysurfer/sdk_types.py
raysurfer/types.py
raysurfer-0.6.3.dist-info/METADATA
raysurfer-0.6.3.dist-info/WHEEL
raysurfer-0.6.3.dist-info/RECORD
