Metadata-Version: 2.4
Name: raysurfer
Version: 0.6.3
Summary: Drop-in replacement for Claude Agent SDK with automatic code caching - just swap your import
Project-URL: Homepage, https://raysurfer.com
Project-URL: Repository, https://github.com/raymondxu/raysurfer-python
Author: Raymond Xu
License-Expression: MIT
Keywords: agents,ai,anthropic,claude,code-blocks,embeddings,retrieval
Classifier: Development Status :: 3 - Alpha
Classifier: Intended Audience :: Developers
Classifier: License :: OSI Approved :: MIT License
Classifier: Programming Language :: Python :: 3
Classifier: Programming Language :: Python :: 3.10
Classifier: Programming Language :: Python :: 3.11
Classifier: Programming Language :: Python :: 3.12
Classifier: Topic :: Software Development :: Libraries :: Python Modules
Requires-Python: >=3.10
Requires-Dist: claude-agent-sdk>=0.1.0
Requires-Dist: httpx>=0.25.0
Requires-Dist: pydantic>=2.0.0
Provides-Extra: dev
Requires-Dist: pytest-asyncio>=0.21.0; extra == 'dev'
Requires-Dist: pytest-httpx>=0.30.0; extra == 'dev'
Requires-Dist: pytest>=7.0.0; extra == 'dev'
Requires-Dist: ruff>=0.1.0; extra == 'dev'
